README.md
setup.py
datatops/__init__.py
datatops/config.py
datatops.egg-info/PKG-INFO
datatops.egg-info/SOURCES.txt
datatops.egg-info/dependency_links.txt
datatops.egg-info/requires.txt
datatops.egg-info/top_level.txt
datatops/server/__init__.py
datatops/server/backend/__init__.py
datatops/server/backend/backend.py
datatops/server/backend/dynamodbbackend.py
datatops/server/backend/jsonfilebackend.py