Metadata-Version: 2.1
Name: datatops
Version: 0.3.0
Summary: Datatops is a super-simple zero-auth zero-setup data storage and retrieval tool for small, low-traffic projects.
Home-page: https://github.com/j6k4m8/datatops/tarball/0.3.0
Author: Jordan Matelsky
Author-email: opensource@matelsky.com
License: Apache 2.0
Keywords: database,serverless
Provides-Extra: aws
